{
    "3": {
        "image": "u.png",
        "name": "Bertha Bradley",
        "email": "zuhe@mailinator.com",
        "phone": "+1 (347) 701-8824",
        "enroll": "+1 (433) 312-5066",
        "datedadmission": "1978-04-06"
    },
    "4": {
        "image": "u.png",
        "name": "Colt Boone",
        "email": "nubeky@mailinator.com",
        "phone": "+1 (164) 134-6027",
        "enroll": "+1 (981) 886-7408",
        "datedadmission": "1976-06-05"
    },
    "5": {
        "image": "u.png",
        "name": "Yetta Boone",
        "email": "cybofyqybe@mailinator.com",
        "phone": "+1 (836) 897-8184",
        "enroll": "+1 (196) 919-5996",
        "datedadmission": "2012-01-23"
    },
    "6": {
        "image": "u.png",
        "name": "Hedwig Tyson",
        "email": "nejupyhiw@mailinator.com",
        "phone": "+1 (101) 689-4615",
        "enroll": "+1 (269) 155-2179",
        "datedadmission": "1991-07-03"
    },
    "7": {
        "image": "u.png",
        "name": "Gil Young",
        "email": "dopoha@mailinator.com",
        "phone": "+1 (157) 298-1958",
        "enroll": "+1 (976) 382-6469",
        "datedadmission": "1983-11-28"
    }
}